Workbook

Sheet 报关单
A1: 中华人民共和国海关出口货物报关单
A2: 预录入编号： | F2: 申报口岸: | I2: 海关编号: | J2: 4403940C53
A3: 境内发货人 | E3: 出境关别 | F3: （5345） | G3: 出口日期 | K3: 申报日期 | O3: 备案号 | U3: 签约地点： | V3: 深圳
A4: 深圳留形科技有限公司 | E4: 深圳湾关 | G4: 46325 | K4: 2026/10/29 | U4: 成交方式: | V4: =I12 -> FOB | W4: SHENZHEN | X4: 付款条件： | Y4: 电汇
A5: 境外收货人 | C5: AEO： | E5: 运输方式 | F5: ( ) | G5: 运输工具名称及航次号 | K5: 提运单号 | U5: 卖方公司： | V5: =A4 -> 深圳留形科技有限公司
A6: Manifold Tech Limited | E6: 公路运输 | U6: 卖方地址： | V6: 深圳市宝安区西乡街道金碧工业区23栋219
A7: 生产销售单位 | C7: =C3 -> 0 | E7: 监管方式 | F7: ( ) | G7: 征免性质 | H7: ( ) | K7: 许可证号 | U7: 卖方电话： | V7: 0755-36802125 | X7: 卖方传真： | Y7: 0755-36802126
A8: =A4 -> 深圳留形科技有限公司 | E8: 一般贸易 | G8: 一般征税 | U8: 买方公司： | V8: =A6 -> Manifold Tech Limited
A9: 合同协议号 | E9: 贸易国(地区) | F9: ( ) | G9: 运抵国(地区) | H9: ( ) | K9: 指运港 | L9: ( ) | O9: 离境口岸 | P9: ( 471401 )跨境的才需要申报 | U9: 买方地址： | V9: UNIT 04,7/F BRIGHT WAY TOWER NO 33 MONG KOK RD KL,HK
A10: SO-2026-1029-1002 | E10: 美国 | G10: 美国 | K10: 美国 | O10: 深圳湾 | U10: 买方电话： | V10: (0852)27636557 | X10: 买方传真： | Y10: (0852)35902333
A11: 包装种类 | C11: ( ) | E11: 件数 | F11: 毛重（千克） | G11: 净重（千克） | I11: 成交方式 | J11: ( ) | K11: 运费 | N11: 保费 | Q11: 杂费 | U11: 报关简称： | X11: 报关全称：
A12: 纸箱 | I12: FOB | T12: 境外收发货人： | W12: 境外收货人通常指签订并执行出口贸易合同中的买方或合同指定的收货人，名称一般填报英文名称，检验检疫要求填报其他外文名称的，在英文名称后填报，以半角括号分隔。
A13: 随附单证及编号 | T13: 境外收发货人代码： | W13: 非互认国家（地区）AEO企业等其他情形，编码免于填报。对于AEO互认国家（地区）企业的，编码填报AEO编码，填报样式按照海关总署发布的相关公告要求填报（如新加坡AEO企业填报样式为：SG123456789012，韩国AEO企业填报样式为KR1234567，具体见相关公告要求）。
A14: 境外收货人完整显示： | D14: =A6 -> Manifold Tech Limited | T14: 检验检疫附加编号： | W14: 通过以下网站输入10位HS编号，再根据申报要素细分确定3位检疫附加编号
A15: 标记唛码及备注： | T15: 检疫局网址-编码查询： | W15: https://e-service.shciq.gov.cn/shesp/
A16: 备注： | T16: 查申报要素网址： | W16: http://www.hscode.net/IntegrateQueries/QueryYS/
L17: 报关联系电话： | T17: 合计： | W17: 贸易国：是指合同买方所在的国家（地区），需填写准确，以后可能会影响收汇。
A18: 特殊关系确认: | D18: 价格影响确认： | F18: 支付特许权使用费: | I18: 自报自缴: | K18: 出口不填 | L18: 原产国/目的国/货源地未注明的项默认与提供的项相同 | T18: =SUM(T20:T471) -> 0 | U18: =SUM(U20:U471) -> 0 | V18: =SUM(V20:V471) -> 1
A19: 项号 | B19: 商品编号 | D19: 商品名称及规格型号 | G19: 数量及单位 | I19: 单价/总价/币制 | K19: 原产国（地区） | M19: 最终目的国（地区） | P19: 境内货源地 | S19: 征免 | T19: 净重 | U19: 毛重 | V19: 件数
A20: 1 | B20: 9031499000 | D20: =IFERROR(INDEX('产品主数据'!$C$2:$C$5,MATCH($B20,'产品主数据'!$A$2:$A$5,0)),"") | G20: 1 | H20: =IFERROR(INDEX('产品主数据'!$F$2:$F$5,MATCH($B20,'产品主数据'!$A$2:$A$5,0)),"") | I20: =IFERROR(INDEX('产品主数据'!$G$2:$G$5,MATCH($B20,'产品主数据'!$A$2:$A$5,0)),"") | K20: 中国 | M20: 中国香港 | P20: 中国深圳 | S20: 照章征税 | T20: =IFERROR(INDEX('产品主数据'!$I$2:$I$5,MATCH($B20,'产品主数据'!$A$2:$A$5,0))*$G20,"") | U20: =IFERROR(INDEX('产品主数据'!$H$2:$H$5,MATCH($B20,'产品主数据'!$A$2:$A$5,0))*$G20,"") | V20: =$G20
A23: 2 | D23: =IFERROR(INDEX('产品主数据'!$C$2:$C$5,MATCH($B23,'产品主数据'!$A$2:$A$5,0)),"") | H23: =IFERROR(INDEX('产品主数据'!$F$2:$F$5,MATCH($B23,'产品主数据'!$A$2:$A$5,0)),"") | I23: =IFERROR(INDEX('产品主数据'!$G$2:$G$5,MATCH($B23,'产品主数据'!$A$2:$A$5,0)),"") | K23: 中国 | M23: 中国香港 | P23: 中国深圳 | S23: 照章征税 | T23: =IFERROR(INDEX('产品主数据'!$I$2:$I$5,MATCH($B23,'产品主数据'!$A$2:$A$5,0))*$G23,"") | U23: =IFERROR(INDEX('产品主数据'!$H$2:$H$5,MATCH($B23,'产品主数据'!$A$2:$A$5,0))*$G23,"") | V23: =$G23
A26: 3 | D26: =IFERROR(INDEX('产品主数据'!$C$2:$C$5,MATCH($B26,'产品主数据'!$A$2:$A$5,0)),"") | H26: =IFERROR(INDEX('产品主数据'!$F$2:$F$5,MATCH($B26,'产品主数据'!$A$2:$A$5,0)),"") | I26: =IFERROR(INDEX('产品主数据'!$G$2:$G$5,MATCH($B26,'产品主数据'!$A$2:$A$5,0)),"") | K26: 中国 | M26: 中国香港 | P26: 中国深圳 | S26: 照章征税 | T26: =IFERROR(INDEX('产品主数据'!$I$2:$I$5,MATCH($B26,'产品主数据'!$A$2:$A$5,0))*$G26,"") | U26: =IFERROR(INDEX('产品主数据'!$H$2:$H$5,MATCH($B26,'产品主数据'!$A$2:$A$5,0))*$G26,"") | V26: =$G26
A29: 4 | D29: =IFERROR(INDEX('产品主数据'!$C$2:$C$5,MATCH($B29,'产品主数据'!$A$2:$A$5,0)),"") | H29: =IFERROR(INDEX('产品主数据'!$F$2:$F$5,MATCH($B29,'产品主数据'!$A$2:$A$5,0)),"") | I29: =IFERROR(INDEX('产品主数据'!$G$2:$G$5,MATCH($B29,'产品主数据'!$A$2:$A$5,0)),"") | K29: 中国 | M29: 中国香港 | P29: 中国深圳 | S29: 照章征税 | T29: =IFERROR(INDEX('产品主数据'!$I$2:$I$5,MATCH($B29,'产品主数据'!$A$2:$A$5,0))*$G29,"") | U29: =IFERROR(INDEX('产品主数据'!$H$2:$H$5,MATCH($B29,'产品主数据'!$A$2:$A$5,0))*$G29,"") | V29: =$G29
A32: 5 | D32: =IFERROR(INDEX('产品主数据'!$C$2:$C$5,MATCH($B32,'产品主数据'!$A$2:$A$5,0)),"") | H32: =IFERROR(INDEX('产品主数据'!$F$2:$F$5,MATCH($B32,'产品主数据'!$A$2:$A$5,0)),"") | I32: =IFERROR(INDEX('产品主数据'!$G$2:$G$5,MATCH($B32,'产品主数据'!$A$2:$A$5,0)),"") | K32: 中国 | M32: 中国香港 | P32: 中国深圳 | S32: 照章征税 | T32: =IFERROR(INDEX('产品主数据'!$I$2:$I$5,MATCH($B32,'产品主数据'!$A$2:$A$5,0))*$G32,"") | U32: =IFERROR(INDEX('产品主数据'!$H$2:$H$5,MATCH($B32,'产品主数据'!$A$2:$A$5,0))*$G32,"") | V32: =$G32
A35: 6 | D35: =IFERROR(INDEX('产品主数据'!$C$2:$C$5,MATCH($B35,'产品主数据'!$A$2:$A$5,0)),"") | H35: =IFERROR(INDEX('产品主数据'!$F$2:$F$5,MATCH($B35,'产品主数据'!$A$2:$A$5,0)),"") | I35: =IFERROR(INDEX('产品主数据'!$G$2:$G$5,MATCH($B35,'产品主数据'!$A$2:$A$5,0)),"") | K35: 中国 | M35: 中国香港 | P35: 中国深圳 | S35: 照章征税 | T35: =IFERROR(INDEX('产品主数据'!$I$2:$I$5,MATCH($B35,'产品主数据'!$A$2:$A$5,0))*$G35,"") | U35: =IFERROR(INDEX('产品主数据'!$H$2:$H$5,MATCH($B35,'产品主数据'!$A$2:$A$5,0))*$G35,"") | V35: =$G35
A38: 7 | D38: =IFERROR(INDEX('产品主数据'!$C$2:$C$5,MATCH($B38,'产品主数据'!$A$2:$A$5,0)),"") | H38: =IFERROR(INDEX('产品主数据'!$F$2:$F$5,MATCH($B38,'产品主数据'!$A$2:$A$5,0)),"") | I38: =IFERROR(INDEX('产品主数据'!$G$2:$G$5,MATCH($B38,'产品主数据'!$A$2:$A$5,0)),"") | K38: 中国 | M38: 中国香港 | P38: 中国深圳 | S38: 照章征税 | T38: =IFERROR(INDEX('产品主数据'!$I$2:$I$5,MATCH($B38,'产品主数据'!$A$2:$A$5,0))*$G38,"") | U38: =IFERROR(INDEX('产品主数据'!$H$2:$H$5,MATCH($B38,'产品主数据'!$A$2:$A$5,0))*$G38,"") | V38: =$G38
A41: 8 | D41: =IFERROR(INDEX('产品主数据'!$C$2:$C$5,MATCH($B41,'产品主数据'!$A$2:$A$5,0)),"") | H41: =IFERROR(INDEX('产品主数据'!$F$2:$F$5,MATCH($B41,'产品主数据'!$A$2:$A$5,0)),"") | I41: =IFERROR(INDEX('产品主数据'!$G$2:$G$5,MATCH($B41,'产品主数据'!$A$2:$A$5,0)),"") | K41: 中国 | M41: 中国香港 | P41: 中国深圳 | S41: 照章征税 | T41: =IFERROR(INDEX('产品主数据'!$I$2:$I$5,MATCH($B41,'产品主数据'!$A$2:$A$5,0))*$G41,"") | U41: =IFERROR(INDEX('产品主数据'!$H$2:$H$5,MATCH($B41,'产品主数据'!$A$2:$A$5,0))*$G41,"") | V41: =$G41
A44: 9 | D44: =IFERROR(INDEX('产品主数据'!$C$2:$C$5,MATCH($B44,'产品主数据'!$A$2:$A$5,0)),"") | H44: =IFERROR(INDEX('产品主数据'!$F$2:$F$5,MATCH($B44,'产品主数据'!$A$2:$A$5,0)),"") | I44: =IFERROR(INDEX('产品主数据'!$G$2:$G$5,MATCH($B44,'产品主数据'!$A$2:$A$5,0)),"") | K44: 中国 | M44: 中国香港 | P44: 中国深圳 | S44: 照章征税 | T44: =IFERROR(INDEX('产品主数据'!$I$2:$I$5,MATCH($B44,'产品主数据'!$A$2:$A$5,0))*$G44,"") | U44: =IFERROR(INDEX('产品主数据'!$H$2:$H$5,MATCH($B44,'产品主数据'!$A$2:$A$5,0))*$G44,"") | V44: =$G44
A47: 10 | D47: =IFERROR(INDEX('产品主数据'!$C$2:$C$5,MATCH($B47,'产品主数据'!$A$2:$A$5,0)),"") | H47: =IFERROR(INDEX('产品主数据'!$F$2:$F$5,MATCH($B47,'产品主数据'!$A$2:$A$5,0)),"") | I47: =IFERROR(INDEX('产品主数据'!$G$2:$G$5,MATCH($B47,'产品主数据'!$A$2:$A$5,0)),"") | K47: 中国 | M47: 中国香港 | P47: 中国深圳 | S47: 照章征税 | T47: =IFERROR(INDEX('产品主数据'!$I$2:$I$5,MATCH($B47,'产品主数据'!$A$2:$A$5,0))*$G47,"") | U47: =IFERROR(INDEX('产品主数据'!$H$2:$H$5,MATCH($B47,'产品主数据'!$A$2:$A$5,0))*$G47,"") | V47: =$G47
A50: 11 | D50: =IFERROR(INDEX('产品主数据'!$C$2:$C$5,MATCH($B50,'产品主数据'!$A$2:$A$5,0)),"") | H50: =IFERROR(INDEX('产品主数据'!$F$2:$F$5,MATCH($B50,'产品主数据'!$A$2:$A$5,0)),"") | I50: =IFERROR(INDEX('产品主数据'!$G$2:$G$5,MATCH($B50,'产品主数据'!$A$2:$A$5,0)),"") | K50: 中国 | M50: 中国香港 | P50: 中国深圳 | S50: 照章征税 | T50: =IFERROR(INDEX('产品主数据'!$I$2:$I$5,MATCH($B50,'产品主数据'!$A$2:$A$5,0))*$G50,"") | U50: =IFERROR(INDEX('产品主数据'!$H$2:$H$5,MATCH($B50,'产品主数据'!$A$2:$A$5,0))*$G50,"") | V50: =$G50
A53: 12 | D53: =IFERROR(INDEX('产品主数据'!$C$2:$C$5,MATCH($B53,'产品主数据'!$A$2:$A$5,0)),"") | H53: =IFERROR(INDEX('产品主数据'!$F$2:$F$5,MATCH($B53,'产品主数据'!$A$2:$A$5,0)),"") | I53: =IFERROR(INDEX('产品主数据'!$G$2:$G$5,MATCH($B53,'产品主数据'!$A$2:$A$5,0)),"") | K53: 中国 | M53: 中国香港 | P53: 中国深圳 | S53: 照章征税 | T53: =IFERROR(INDEX('产品主数据'!$I$2:$I$5,MATCH($B53,'产品主数据'!$A$2:$A$5,0))*$G53,"") | U53: =IFERROR(INDEX('产品主数据'!$H$2:$H$5,MATCH($B53,'产品主数据'!$A$2:$A$5,0))*$G53,"") | V53: =$G53
A56: 13 | D56: =IFERROR(INDEX('产品主数据'!$C$2:$C$5,MATCH($B56,'产品主数据'!$A$2:$A$5,0)),"") | H56: =IFERROR(INDEX('产品主数据'!$F$2:$F$5,MATCH($B56,'产品主数据'!$A$2:$A$5,0)),"") | I56: =IFERROR(INDEX('产品主数据'!$G$2:$G$5,MATCH($B56,'产品主数据'!$A$2:$A$5,0)),"") | K56: 中国 | M56: 中国香港 | P56: 中国深圳 | S56: 照章征税 | T56: =IFERROR(INDEX('产品主数据'!$I$2:$I$5,MATCH($B56,'产品主数据'!$A$2:$A$5,0))*$G56,"") | U56: =IFERROR(INDEX('产品主数据'!$H$2:$H$5,MATCH($B56,'产品主数据'!$A$2:$A$5,0))*$G56,"") | V56: =$G56
... A137: 40 | D137: =IFERROR(INDEX('产品主数据'!$C$2:$C$5,MATCH($B137,'产品主数据'!$A$2:$A$5,0)),"") | H137: =IFERROR(INDEX('产品主数据'!$F$2:$F$5,MATCH($B137,'产品主数据'!$A$2:$A$5,0)),"") | I137: =IFERROR(INDEX('产品主数据'!$G$2:$G$5,MATCH($B137,'产品主数据'!$A$2:$A$5,0)),"") | K137: 中国 | M137: 中国香港 | P137: 中国深圳 | S137: 照章征税 | T137: =IFERROR(INDEX('产品主数据'!$I$2:$I$5,MATCH($B137,'产品主数据'!$A$2:$A$5,0))*$G137,"") | U137: =IFERROR(INDEX('产品主数据'!$H$2:$H$5,MATCH($B137,'产品主数据'!$A$2:$A$5,0))*$G137,"") | V137: =$G137
A140: 45
A143: 46
A146: 47
A149: 48
A152: 49
A155: 50
BY170: 表格制作单位：深圳市长来运报关有限公司QQ1152276688

Sheet 申报要素
A1: (产品或者包装上有明显的logo，带R，TM标识的商标必须申报为品牌，有显示型号（model，type no.）的必须申报为型号)(申报的牌子型号要在产品或包装上有一模一样显示，海关查货的话会去比对拍照，对不上会升级整车查验和压车改单）
A2: (申报的牌子型号要在产品或包装上有一模一样显示，海关查货的话会去比对拍照，对不上会升级整车查验和压车改单）
A3: 检验检疫附加编号：通过以下网站输入10位HS编号，再根据申报要素细分确定3位检疫附加编号
B4: https://e-service.shciq.gov.cn/shesp/ | C4: https://e-service.shciq.gov.cn/shesp/
A5: 申报要素查询网址： | C5: http://www.hscode.net/IntegrateQueries/QueryYS/
A8: 申报要素
A9: 序号 | B9: 品名 | C9: 海关HS编码 | D9: 检疫附加码 | E9: 品牌 | F9: 型号 | G9: 品牌类型 | H9: 出口享惠情况 | I9: 其他申报要素
A10: 1 | B10: =报关单!D20 | C10: =报关单!B20 | E10: =IFERROR(INDEX('产品主数据'!$D$2:$D$5,MATCH(报关单!$B$20,'产品主数据'!$A$2:$A$5,0)),"") | F10: =IFERROR(INDEX('产品主数据'!$E$2:$E$5,MATCH(报关单!$B$20,'产品主数据'!$A$2:$A$5,0)),"") | G10: 境内自主品牌 | H10: 不能确定在最终目的国（地区）享受优惠关税 | I10: 用于扫描

Sheet 发票
C1: Shen Zhen Liuxing Technology Co., Ltd
C2: 503，5/F, Building A, North District, Qianhai Shenzhen-Hong Kong Youth Innovation and Enterpreneur Hub, Shenzhen, Guangdong Province, China
A3: COMMERCIAL INVOICE
A4: Customer Manifold Tech Limited | H4: Invoice No. ： | I4: INV-202610-0145
A5: Address ：Unit 861 of 8th Floor Bldg 8，Hong Kong-Shenzhen Innovation Technology Park Lok Ma Chau，NT, Hong Kong | H5: Invoice Date ： | I5: 46324
A7: Attention ：Aaron QIN | H7: Currency ： | I7: USD
A8: Tel No. ： 18823420475 | H8: Reference ： | I8: =报关单!A10
A9: No. | B9: Description | E9: HS Code | F9: Quantity | G9: Unit Price | I9: Amount
A10: 1 | B10: =报关单!D20 | E10: =报关单!B20 | F10: =报关单!G20 | G10: =报关单!I20 | I10: =G10*F10 -> 564.44
A11: Total | F11: 1 | I11: =SUM(I10:I10) -> 564.44
A12: Remark:
A13: Name of Beneficiary: Shen Zhen Liuxing Technology Co., Ltd Bank: China Merchants Bank Co., Ltd.
A14: Beneficiary Account No:755976996810001 Swift Code:CMBCCNBS050
A15: Terms of payment:
A16: -The remitting parties should bear remitance charge
A17: -An interest charge of 2% per month may be imposed for overdue balances.
A18: For and on Behalf of Shen Zhen Liuxing Technology Co., Ltd

Sheet 箱单
B2: 装 箱 单 PACKING LIST
H3: 日期 Date： | I3: 46324
H4: 发票编号 Invoice No: | I4: =发票!I4 -> INV-202610-0145
A5: 客户 To Messrs: | B5: Manifold Tech Limited | H5: 合同号 Contract No: | I5: =报关单!A10
A7: 船名 Shipped by： | C7: 由 | D7: 香港 | E7: 至 | F7: 美国 | H7: 付款条件 Terms of Payment: | I7: =报关单!Y4 -> 电汇
A9: 箱号 Ctn.No. | B9: 货物名称及规格 Description | C9: 箱数： Pkg： | F9: 数量： Ge.Quantity | H9: 毛重(KG)： G.W.(KG): | I9: 净重(KG)： N.W.(KG):
A10: 1 | B10: =报关单!D20 | C10: =报关单!V20 | F10: =报关单!G20 | G10: =报关单!H20 | H10: =报关单!U20 | I10: =报关单!T20
C11: =OFFSET(报关单!$V$1,ROW(报关单!V9)*3+16,0) -> 0 | H11: =OFFSET(报关单!$U$1,ROW(报关单!U9)*3+16,0) -> 0 | I11: =OFFSET(报关单!$T$1,ROW(报关单!T9)*3+16,0) -> 0
C12: =OFFSET(报关单!$V$1,ROW(报关单!V10)*3+16,0) -> 0 | H12: =OFFSET(报关单!$U$1,ROW(报关单!U10)*3+16,0) -> 0 | I12: =OFFSET(报关单!$T$1,ROW(报关单!T10)*3+16,0) -> 0
C13: =OFFSET(报关单!$V$1,ROW(报关单!V11)*3+16,0) -> 0 | H13: =OFFSET(报关单!$U$1,ROW(报关单!U11)*3+16,0) -> 0 | I13: =OFFSET(报关单!$T$1,ROW(报关单!T11)*3+16,0) -> 0
C14: =OFFSET(报关单!$V$1,ROW(报关单!V12)*3+16,0) -> 0 | H14: =OFFSET(报关单!$U$1,ROW(报关单!U12)*3+16,0) -> 0 | I14: =OFFSET(报关单!$T$1,ROW(报关单!T12)*3+16,0) -> 0
C15: =OFFSET(报关单!$V$1,ROW(报关单!V13)*3+16,0) -> 0 | H15: =OFFSET(报关单!$U$1,ROW(报关单!T13)*3+16,0) -> 0 | I15: =OFFSET(报关单!$T$1,ROW(报关单!T13)*3+16,0) -> 0
C16: =OFFSET(报关单!$V$1,ROW(报关单!V14)*3+16,0) -> 0 | H16: =OFFSET(报关单!$U$1,ROW(报关单!T14)*3+16,0) -> 0 | I16: =OFFSET(报关单!$T$1,ROW(报关单!T14)*3+16,0) -> 0
C17: =OFFSET(报关单!$V$1,ROW(报关单!T15)*3+16,0) -> 0
C18: =OFFSET(报关单!$V$1,ROW(报关单!T16)*3+16,0) -> 0
A19: 合计 Total | C19: =SUM(C10:C18) -> 0 | F19: =SUM(F10:F18) -> 1 | G19: =SUM(G10:G18) -> 0 | H19: =SUM(H10:H18) -> 0 | I19: =SUM(I10:I18) -> 0
A20: 唛头 Marks

Sheet 合同
B1: 合 同 SALES CONTRACT
B2: 卖 方： | C2: =报关单!V5 -> 深圳留形科技有限公司
B3: Sellers:
B4: 地 址： | C4: 广东省深圳市南山区南山街道桂湾社区梦海大道5188号前海深港青年梦工场北区A栋5楼503
B5: Address: | F5: 合同号码
B6: 电 话： | D6: 传 真 | F6: Contract No: | G6: SO-2026-1029-1002
B7: TEL: | D7: FAX: | F7: 日 期 | G7: 46323
B8: 买 方： | C8: =报关单!V8 -> Manifold Tech Limited | F8: Date:
B9: Buyers： | F9: 签约地点 | G9: 中国深圳
B10: 地 址： | C10: 香港新界落马洲港深创新及科技园8号楼8楼206单元3室 | F10: Signed at:
B11: Address: | F11: 成交方式： Trade Term: | G11: =报关单!V4 -> FOB
B12: 电 话 | D12: 传 真
B13: TEL: | D13: FAX:
B14: 经买卖双方确认根据下列条款订立本合同
B15: This contract is made out by the Sellers and Buyers as per the following terms and conditions mutuilly confirmed:
B16: (1)货物名称 | D16: (2) 数 量 | E16: (3)单 位 | F16: (4)单价 | G16: (5) 金 额
B17: Name of commodity | D17: Quantity | E17: Unit | F17: Unit Price | G17: Amount
B18: =报关单!D20 | D18: =报关单!G20 | E18: =报关单!H20 | F18: =报关单!I20 | G18: =F18*D18 -> 564.44
F33: 总 值 | G33: =SUM(G18:G32) -> 564.44
F34: Total Amount:
B40: 买 方 | E40: 卖 方
B41: THE BUYERS | E41: THE SELLERS
B42: (Authorized Signature) | E42: (Authorized Signature)

Sheet 不报关填写快递  B19发票
A1: COMMERCIAL INVOICE | J1: 固定模板填写需注意事项: 1.品名申报行数如多出需删掉空余行数（例如：只有2项品名，需删掉剩余空白的6项行数）
A2: Order No.单号 | E2: Date of Exportation
A3: Coutry of Origin | B3: CN | E3: pieceCount总件数
A4: Shipper Information（寄件人）
A5: Company 公司:
A6: Contact 联系人: | E6: TEL电话： | J6: 国家要一定填二字代码
A7: Address 详细地址:
A8: Consignee Information(收货人)
A9: Company 公司: | E9: VAT/TAX ID税号：
A10: Contact 联系人： | B10: Tobias Fischer | E10: TEL 电话：
A11: Country 目的国: | B11: AU | E11: State 州省： | G11: QLD
A12: City 城市： | B12: Kelvin Grove | E12: Zip Code 邮编: | G12: 4059
A13: 收件人邮箱: | B13: tobias.fischer@qut.edu.au
A14: Address详细地址1: | B14: QUT Kelvin Grove Campus F Block, Level 1 Boundary Road Kelvin Grove QLD, 4059 Australia
A15: Address详细地址2:
A16: Address详细地址:3
A17: FBA单号 | B17: DESCRIPTION OF GOODS品名 | C17: DESCRIPTION OF GOODS中文品名 | D17: Material英文材质 | E17: Use英文用途 | F17: HS Code 海关编码 | G17: Qty (pcs) 数量 | H17: Unit Price(usd) 单价 | I17: Total（USD）总价
B18: Spatial Memory Module | C18: 空间记忆模组 | D18: ABS | E18: Scanning measure | F18: 9031499000 | G18: 1 | H18: 999 | I18: =H18*G18 -> 999
A19: Freight运费:
A20: declaretotal申报总额 | I20: =I18 -> 999
A21: Total:
A22: SHIPPER’S SIGNATURE & STAMP:

Sheet 产品主数据
A1: HS编码 | B1: ERP商品编码 | C1: 品名(中) | D1: 品牌 | E1: 型号(规格) | F1: 单位 | G1: 单价USD | H1: 单件毛重KG | I1: 单件净重KG
A2: 9031499000 | B2: TJ00033 | C2: 空间记忆模组 | D2: 留形 | E2: Odin1 | F2: 套 | G2: 564.44 | H2: 0 | I2: 0
B3: TJ00004 | C3: 三维激光扫描仪 | F3: 套 | G3: 1898.99 | H3: 0 | I3: 0
B4: CP00020 | C4: 细目相机模块 | F4: 个 | G4: 95.0 | H4: 0 | I4: 0
B5: ZCP00017 | C5: 新款P2 Pro RTK模块 | F5: PCS | G5: 147.79 | H5: 0 | I5: 0
